grachev/__init__.py
grachev/__main__.py
grachev/cli.py
grachev-0.0.0.dist-info/AUTHORS.rst
grachev-0.0.0.dist-info/LICENSE
grachev-0.0.0.dist-info/METADATA
grachev-0.0.0.dist-info/WHEEL
grachev-0.0.0.dist-info/entry_points.txt
grachev-0.0.0.dist-info/top_level.txt
grachev-0.0.0.dist-info/RECORD
