Metadata-Version: 2.1
Name: grachev
Version: 0.0.0
Summary: Grachev package
Home-page: https://github.com/aljeshishe/python-grachev
Author: Aleksei Grachev
Author-email: ax66@bk.ru
License: BSD-2-Clause
Project-URL: Documentation, https://python-grachev.readthedocs.io/
Project-URL: Changelog, https://python-grachev.readthedocs.io/en/latest/changelog.html
Project-URL: Issue Tracker, https://github.com/aljeshishe/python-grachev/issues
Platform: UNKNOWN
Classifier: Development Status :: 5 - Production/Stable
Classifier: Intended Audience :: Developers
Classifier: License :: OSI Approved :: BSD License
Classifier: Operating System :: Unix
Classifier: Operating System :: POSIX
Classifier: Operating System :: Microsoft :: Windows
Classifier: Programming Language :: Python
Classifier: Programming Language :: Python :: 2.7
Classifier: Programming Language :: Python :: 3
Classifier: Programming Language :: Python :: 3.5
Classifier: Programming Language :: Python :: 3.6
Classifier: Programming Language :: Python :: 3.7
Classifier: Programming Language :: Python :: 3.8
Classifier: Programming Language :: Python :: Implementation :: CPython
Classifier: Programming Language :: Python :: Implementation :: PyPy
Classifier: Topic :: Utilities
Requires-Python: >=2.7, !=3.0.*, !=3.1.*, !=3.2.*, !=3.3.*, !=3.4.*
Requires-Dist: click
